hexon_mini/__init__.py
hexon_mini/hexon_mini_client.py
tests/__init__.py
tests/test_hexon_mini.py
hexon_mini-0.1.2.dist-info/LICENSE
hexon_mini-0.1.2.dist-info/METADATA
hexon_mini-0.1.2.dist-info/WHEEL
hexon_mini-0.1.2.dist-info/top_level.txt
hexon_mini-0.1.2.dist-info/RECORD
